inspect313/__init__.py
inspect313/py.typed
inspect313-0.1.0.dist-info/LICENSE
inspect313-0.1.0.dist-info/METADATA
inspect313-0.1.0.dist-info/WHEEL
inspect313-0.1.0.dist-info/RECORD
