Metadata-Version: 2.1
Name: inspect313
Version: 0.1.0
Summary: Backport of `inspect` module from Python3.13
Home-page: https://github.com/wemake-services/inspect313
License: MIT
Keywords: inspect,python,signature,backport
Author: sobolevn
Author-email: mail@sobolevn.me
Requires-Python: >=3.8,<4.0
Classifier: Development Status :: 3 - Alpha
Classifier: Intended Audience :: Developers
Classifier: License :: OSI Approved :: MIT License
Classifier: Operating System :: OS Independent
Classifier: Programming Language :: Python :: 3
Classifier: Programming Language :: Python :: 3.8
Classifier: Programming Language :: Python :: 3.9
Classifier: Programming Language :: Python :: 3.10
Classifier: Programming Language :: Python :: 3.11
Classifier: Programming Language :: Python :: 3.12
Classifier: Topic :: Software Development :: Libraries :: Python Modules
Requires-Dist: typing-extensions (>=4.10,<5.0)
Project-URL: Repository, https://github.com/wemake-services/inspect313
